README.md
setup.py
SuperalloyDataExtractor.egg-info/PKG-INFO
SuperalloyDataExtractor.egg-info/SOURCES.txt
SuperalloyDataExtractor.egg-info/dependency_links.txt
SuperalloyDataExtractor.egg-info/top_level.txt
superalloydataextractor/__init__.py
superalloydataextractor/data_extraction/Phrase_parse.py
superalloydataextractor/data_extraction/Relation_extraciton.py
superalloydataextractor/data_extraction/T_pre_processor.py
superalloydataextractor/data_extraction/__init__.py
superalloydataextractor/data_extraction/dictionary.py
superalloydataextractor/data_extraction/file_io.py
superalloydataextractor/data_extraction/get_all_attributes.py
superalloydataextractor/data_extraction/get_full_text.py
superalloydataextractor/data_extraction/pre_processor.py
superalloydataextractor/data_extraction/sentence_positioner.py
superalloydataextractor/elsevier_articles_archive/__init__.py
superalloydataextractor/elsevier_articles_archive/article_dois.py
superalloydataextractor/word_embedding/__init__.py
superalloydataextractor/word_embedding/load_word2vec.py