Metadata-Version: 2.1
Name: SuperalloyDataExtractor
Version: 0.0.6
Summary: A data extractor to get target information from superalloy documents. The functions include batch downloading documents in XML and TXT format from the Elsevier database, locating target sentences from the full text and automatically extracting triple information in the form of <material name, property specifier, value>.
Home-page: https://github.com/Weiren1996/superalloydataextractor
Author: Weiren_Wang
Author-email: 357329191@qq.com
License: MIT
Keywords: text-mining,mining,superalloy,informatics,nlp,txt,science,scientific
Platform: UNKNOWN
Classifier: Environment :: Web Environment
Classifier: Intended Audience :: Science/Research
Classifier: Operating System :: Microsoft :: Windows
Classifier: Programming Language :: Python :: 3
Classifier: Topic :: Internet
Classifier: Topic :: Scientific/Engineering
Classifier: Topic :: Text Processing
Requires-Python: >=3.6
